[
    {
      "Shell": {
        "outside": {
          "Statement": {
            "variant": {
              "Token": [
                "Template",
                0
              ]
            },
            "context": {
              "Literal": [
                "DAY",
                9
              ]
            },
            "child": null
          }
        },
        "inside": [
          {
            "Statement": {
              "variant": {
                "Token": [
                  "StringType",
                  17
                ]
              },
              "context": {
                "Literal": [
                  "First",
                  24
                ]
              },
              "child": {
                "Statement": {
                  "variant": {
                    "Token": [
                      "Value",
                      32
                    ]
                  },
                  "context": {
                    "Literal": [
                      "Nothing",
                      38
                    ]
                  },
                  "child": null
                }
              }
            }
          },
          {
            "Statement": {
              "variant": {
                "Token": [
                  "StringType",
                  50
                ]
              },
              "context": {
                "Literal": [
                  "Second",
                  57
                ]
              },
              "child": {
                "Statement": {
                  "variant": {
                    "Token": [
                      "Value",
                      66
                    ]
                  },
                  "context": {
                    "Literal": [
                      "Nothing",
                      72
                    ]
                  },
                  "child": null
                }
              }
            }
          },
          {
            "Statement": {
              "variant": {
                "Token": [
                  "StringType",
                  84
                ]
              },
              "context": {
                "Literal": [
                  "Third",
                  91
                ]
              },
              "child": {
                "Statement": {
                  "variant": {
                    "Token": [
                      "Value",
                      99
                    ]
                  },
                  "context": {
                    "Literal": [
                      "Nothing",
                      105
                    ]
                  },
                  "child": null
                }
              }
            }
          },
          {
            "Statement": {
              "variant": {
                "Token": [
                  "IntegerType",
                  117
                ]
              },
              "context": {
                "Literal": [
                  "Day",
                  125
                ]
              },
              "child": {
                "Statement": {
                  "variant": {
                    "Token": [
                      "Value",
                      131
                    ]
                  },
                  "context": {
                    "Int": [
                      1,
                      137
                    ]
                  },
                  "child": null
                }
              }
            }
          },
          {
            "Statement": {
              "variant": {
                "Token": [
                  "FloatType",
                  141
                ]
              },
              "context": {
                "Literal": [
                  "Seconds",
                  147
                ]
              },
              "child": null
            }
          }
        ]
      }
    },
    {
      "Statement": {
        "variant": {
          "Token": [
            "Create",
            173
          ]
        },
        "context": {
          "Literal": [
            "Monday",
            180
          ]
        },
        "child": {
          "Statement": {
            "variant": {
              "Token": [
                "Template",
                189
              ]
            },
            "context": {
              "Literal": [
                "DAY",
                198
              ]
            },
            "child": null
          }
        }
      }
    },
    {
      "Shell": {
        "outside": {
          "Statement": {
            "variant": {
              "Token": [
                "Select",
                208
              ]
            },
            "context": {
              "Literal": [
                "Monday",
                215
              ]
            },
            "child": null
          }
        },
        "inside": [
          {
            "Statement": {
              "variant": {
                "Token": [
                  "Set",
                  227
                ]
              },
              "context": {
                "Literal": [
                  "First",
                  231
                ]
              },
              "child": {
                "Statement": {
                  "variant": {
                    "Token": [
                      "Value",
                      239
                    ]
                  },
                  "context": {
                    "Literal": [
                      "Science",
                      245
                    ]
                  },
                  "child": null
                }
              }
            }
          },
          {
            "Statement": {
              "variant": {
                "Token": [
                  "Set",
                  257
                ]
              },
              "context": {
                "Literal": [
                  "Second",
                  261
                ]
              },
              "child": {
                "Statement": {
                  "variant": {
                    "Token": [
                      "Value",
                      270
                    ]
                  },
                  "context": {
                    "Literal": [
                      "CS",
                      276
                    ]
                  },
                  "child": null
                }
              }
            }
          }
        ]
      }
    },
    {
      "Statement": {
        "variant": {
          "Token": [
            "Create",
            300
          ]
        },
        "context": {
          "Literal": [
            "Tuesday",
            307
          ]
        },
        "child": {
          "Statement": {
            "variant": {
              "Token": [
                "Instance",
                317
              ]
            },
            "context": {
              "Literal": [
                "Monday",
                326
              ]
            },
            "child": null
          }
        }
      }
    },
    {
      "Statement": {
        "variant": {
          "Token": [
            "Query",
            339
          ]
        },
        "context": {
          "Literal": [
            "DAY",
            345
          ]
        },
        "child": {
          "Statement": {
            "variant": {
              "Token": [
                "From",
                351
              ]
            },
            "context": {
              "Token": [
                "Template",
                356
              ]
            },
            "child": null
          }
        }
      }
    },
    {
      "Statement": {
        "variant": {
          "Token": [
            "Query",
            369
          ]
        },
        "context": {
          "Literal": [
            "Monday",
            375
          ]
        },
        "child": {
          "Statement": {
            "variant": {
              "Token": [
                "From",
                384
              ]
            },
            "context": {
              "Token": [
                "Instance",
                389
              ]
            },
            "child": null
          }
        }
      }
    }
  ]